rtfsig/__init__.py
rtfsig/app.py
rtfsig/core.py
rtfsig/yara.py
rtfsig-0.1.4.dist-info/licenses/LICENSE-2.0.txt
tests/__init__.py
tests/test_parsing.py
tests/test_yara.py
rtfsig-0.1.4.dist-info/METADATA
rtfsig-0.1.4.dist-info/WHEEL
rtfsig-0.1.4.dist-info/entry_points.txt
rtfsig-0.1.4.dist-info/top_level.txt
rtfsig-0.1.4.dist-info/RECORD
