Metadata-Version: 2.4
Name: rtfsig
Version: 0.1.4
Summary: Extract potentially unique strings from RTF files for threat hunting
Home-page: https://github.com/PwCUK-CTO/rtfsig
Author: David Cannings
Author-email: david@edeca.net
Classifier: Programming Language :: Python :: 3
Classifier: License :: OSI Approved :: Apache Software License
Classifier: Environment :: Console
Classifier: Operating System :: OS Independent
Classifier: Development Status :: 4 - Beta
Classifier: Topic :: Security
License-File: LICENSE-2.0.txt
Requires-Dist: Jinja2==3.1.6
Provides-Extra: docs
Provides-Extra: tests
Requires-Dist: pylint; extra == "tests"
Requires-Dist: pytest; extra == "tests"
Requires-Dist: pytest-cov; extra == "tests"
Requires-Dist: plyara; extra == "tests"
Provides-Extra: dev
Requires-Dist: black; extra == "dev"
Requires-Dist: tox; extra == "dev"
Requires-Dist: twine; extra == "dev"
Requires-Dist: wheel; extra == "dev"
Requires-Dist: pylint; extra == "dev"
Requires-Dist: pytest; extra == "dev"
Requires-Dist: pytest-cov; extra == "dev"
Requires-Dist: plyara; extra == "dev"
Dynamic: author
Dynamic: author-email
Dynamic: classifier
Dynamic: description
Dynamic: description-content-type
Dynamic: home-page
Dynamic: license-file
Dynamic: provides-extra
Dynamic: requires-dist
Dynamic: summary
